Metadata-Version: 2.1
Name: pyobjconfig
Version: 0.1.4
Summary: An argparse+pydantic-based configuration system for Python.
Home-page: https://github.com/wwoods/pyobjconfig
Author: Walt Woods
Author-email: woodswalben@gmail.com
License-File: LICENSE
